crypting/__init__.py
crypting/Ciphers/__init__.py
crypting/Ciphers/binary.py
crypting/Ciphers/caesar.py
crypting/Ciphers/chacha20.py
crypting/Ciphers/des.py
crypting/Ciphers/enigma.py
crypting/Ciphers/hill.py
crypting/Ciphers/monoalphabetic.py
crypting/Ciphers/polyalphabetic.py
crypting/Ciphers/rc4.py
crypting/Ciphers/rc5.py
crypting/Ciphers/rc6.py
crypting/Ciphers/salsa20.py
crypting/Ciphers/transposition.py
crypting/Ciphers/triple_des.py
crypting/Hash/__init__.py
crypting/Hash/md5.py
crypting-1.5.10.dist-info/LICENSE
crypting-1.5.10.dist-info/METADATA
crypting-1.5.10.dist-info/WHEEL
crypting-1.5.10.dist-info/top_level.txt
crypting-1.5.10.dist-info/RECORD
