Metadata-Version: 2.1
Name: crypting
Version: 1.5.10
Summary: A comprehensive encryption/decryption library
Home-page: https://github.com/Elabsurdo984/Pycrypter.git
Author: Elabsurdo984
Author-email: matiassfernandez00@gmail.com
Requires-Python: >=3.6
License-File: LICENSE
Requires-Dist: pycryptodome>=3.21.0
Requires-Dist: numpy>=2.0.2
